pdp/__init__.py
pdp/__main__.py
pdp/config_utils.py
pdp/py.typed
pdp/spec.py
pdp/cli/__init__.py
pdp/cli/cli_run.py
pdp/cli/commands/__init__.py
pdp/cli/commands/collect_command.py
pdp/cli/commands/dataset_command.py
pdp/cli/commands/download_command.py
pdp/cli/commands/ls_command.py
pdp/cli/commands/package_command.py
pdp/cli/commands/root_command.py
pdp/cli/commands/update_command.py
pdp/cli/commands/upload_command.py
pdp/cli/commands/validate_command.py
pdp/data_utils/__init__.py
pdp/data_utils/collect_utils.py
pdp/data_utils/download_utils.py
pdp/data_utils/file_utils.py
pdp/data_utils/job_utils.py
pdp/data_utils/manifest_utils.py
pdp/data_utils/query_utils.py
pdp/data_utils/readme_utils.py
pdp/data_utils/schema_utils.py
pdp/data_utils/update_utils.py
pdp/datasets/__init__.py
pdp/datasets/contracts/__init__.py
pdp/datasets/contracts/contracts_collect.py
pdp/datasets/contracts/contracts_queries.py
pdp/datasets/contracts/contracts_spec.py
pdp/datasets/native_transfers/__init__.py
pdp/datasets/native_transfers/native_transfers_collect.py
pdp/datasets/native_transfers/native_transfers_queries.py
pdp/datasets/native_transfers/native_transfers_spec.py
pdp/datasets/slots/__init__.py
pdp/datasets/slots/slots_collect.py
pdp/datasets/slots/slots_queries.py
pdp/datasets/slots/slots_spec.py
paradigm_data_portal-0.2.2.dist-info/entry_points.txt
paradigm_data_portal-0.2.2.dist-info/LICENSE-APACHE
paradigm_data_portal-0.2.2.dist-info/LICENSE-MIT
paradigm_data_portal-0.2.2.dist-info/WHEEL
paradigm_data_portal-0.2.2.dist-info/METADATA
paradigm_data_portal-0.2.2.dist-info/RECORD
