Metadata-Version: 2.1
Name: paradigm-data-portal
Version: 0.2.2
Summary: pdp downloads and manages datasets from the Paradigm Data Portal
Requires-Python: >=3.7
Classifier: Development Status :: 4 - Beta
Classifier: Intended Audience :: Developers
Classifier: Intended Audience :: Financial and Insurance Industry
Classifier: Intended Audience :: Science/Research
Classifier: License :: OSI Approved :: Apache Software License
Classifier: License :: OSI Approved :: MIT License
Classifier: Natural Language :: English
Classifier: Operating System :: MacOS
Classifier: Operating System :: Microsoft :: Windows
Classifier: Operating System :: POSIX :: Linux
Classifier: Programming Language :: Python :: 3.7
Classifier: Programming Language :: Python :: 3.8
Classifier: Programming Language :: Python :: 3.9
Classifier: Programming Language :: Python :: 3.10
Classifier: Programming Language :: Python :: 3.11
Classifier: Typing :: Typed
Requires-Dist: typing-extensions >=4.2.0, <5
Requires-Dist: requests >=2.20.0, <3
Requires-Dist: toolcli >=0.6.13, <0.7
Requires-Dist: toolstr >=0.9.3, <0.10
Requires-Dist: tooljob >=0.1.6, <0.2
Requires-Dist: mypy ==1.2.0 ; extra == "test"
Requires-Dist: mypy_extensions >= 1.0.0, <1.1.0 ; extra == "test"
Requires-Dist: pytest >=6, <7 ; extra == "test"
Provides-Extra: test
